ebbef2p/__init__.py
ebbef2p/beam.py
ebbef2p/distributed_load.py
ebbef2p/elastic_foundation_support.py
ebbef2p/element.py
ebbef2p/helpers.py
ebbef2p/nodal_load.py
ebbef2p/nodal_support.py
ebbef2p/soil_conditions.py
ebbef2p/structure.py
ebbef2p/vlasov_foundation_parameters.py
tests/__init__.py
tests/test_beam.py
tests/test_structure.py
ebbef2p_python-0.0.2.dev1.dist-info/LICENSE
ebbef2p_python-0.0.2.dev1.dist-info/METADATA
ebbef2p_python-0.0.2.dev1.dist-info/WHEEL
ebbef2p_python-0.0.2.dev1.dist-info/top_level.txt
ebbef2p_python-0.0.2.dev1.dist-info/RECORD
