Metadata-Version: 2.1
Name: ebbef2p-python
Version: 0.0.2.dev1
Summary: Tool for Finite Element Analysis of beams on elastic foundations
Home-page: https://github.com/bteodoru/ebbef2p-python
Author: Bogdan Teodoru
Author-email: bteodoru@gmail.com
License: UNKNOWN
Keywords: finite element method,math,numerics,elastic foundation
Platform: UNKNOWN
Classifier: Development Status :: 4 - Beta
Classifier: Programming Language :: Python :: 3
Classifier: License :: OSI Approved :: MIT License
Classifier: Operating System :: OS Independent
Classifier: Environment :: Console
Classifier: Intended Audience :: Developers
Classifier: Intended Audience :: Education
Classifier: Intended Audience :: Science/Research
Classifier: Topic :: Scientific/Engineering
Requires-Python: >=3.6
Requires-Dist: numpy
Requires-Dist: matplotlib
